{
  "variables": {
    "aws_access_key": "",
    "aws_secret_key": ""
  },

  "builders": [{
    "ssh_pty" : "true",
    "type": "amazon-ebs",
    "access_key": "{{user `aws_access_key`}}",
    "secret_key": "{{user `aws_secret_key`}}",
    "region": "us-east-1",
    "source_ami": "ami-6d1c2007",
    "ami_virtualization_type": "hvm",
    "instance_type": "t2.small",
    "ssh_username": "centos",
    "ami_name": "packer-example {{timestamp}}",
    "vpc_id": "vpc-ac6353c8",
    "subnet_id": "subnet-1247f64a",
    "associate_public_ip_address": true
  }],

  "provisioners": [
    {
      "type": "shell",
      "inline": [ "sudo yum update -y" ]
    }
  ]
}
